pamiq_vrchat/__init__.py
pamiq_vrchat/py.typed
pamiq_vrchat/utils.py
pamiq_vrchat/actuators/__init__.py
pamiq_vrchat/actuators/control_models.py
pamiq_vrchat/actuators/mouse.py
pamiq_vrchat/actuators/osc.py
pamiq_vrchat/sensors/__init__.py
pamiq_vrchat/sensors/audio.py
pamiq_vrchat/sensors/image.py
pamiq_vrchat-0.1.0.dist-info/METADATA
pamiq_vrchat-0.1.0.dist-info/WHEEL
pamiq_vrchat-0.1.0.dist-info/licenses/LICENSE
pamiq_vrchat-0.1.0.dist-info/RECORD
