Metadata-Version: 2.4
Name: pamiq-vrchat
Version: 0.1.0
Summary: Interface for PAMIQ to interact with VRChat
Project-URL: Repository, https://github.com/MLShukai/pamiq-vrchat
Project-URL: Issues, https://github.com/MLShukai/pamiq-vrchat/issues
License: MIT License
License-File: LICENSE
Keywords: AI,Agent,Autonomous Machine Intelligence,IO,Interface,ML,Machine Learning,PAMIQ,VRChat,pamiq
Classifier: Development Status :: 3 - Alpha
Classifier: Intended Audience :: Developers
Classifier: Intended Audience :: Science/Research
Classifier: License :: OSI Approved :: MIT License
Classifier: Natural Language :: English
Classifier: Natural Language :: Japanese
Classifier: Operating System :: Microsoft :: Windows
Classifier: Operating System :: POSIX :: Linux
Classifier: Programming Language :: Python :: 3
Classifier: Programming Language :: Python :: 3.12
Classifier: Programming Language :: Python :: 3.13
Classifier: Programming Language :: Python :: 3.14
Requires-Python: >=3.12
Requires-Dist: cv2-enumerate-cameras>=1.1.18.3
Requires-Dist: inputtino-python; sys_platform == 'linux'
Requires-Dist: pamiq-core>=0.3.1
Requires-Dist: pamiq-io[inputtino,opencv,osc,soundcard,windows]>=0.6.1
Requires-Dist: pycaw>=20240210; sys_platform == 'win32'
Provides-Extra: sample
Requires-Dist: colorlog>=6.9.0; extra == 'sample'
Requires-Dist: mlflow>=2.22.0; extra == 'sample'
Requires-Dist: pamiq-core[kbctl,torch]>=0.3.1; extra == 'sample'
Requires-Dist: rootutils>=1.0.7; extra == 'sample'
Requires-Dist: tensordict>=0.8.2; extra == 'sample'
Requires-Dist: torchaudio>=2.7.0; extra == 'sample'
Requires-Dist: torchvision>=0.22.0; extra == 'sample'
Requires-Dist: tyro>=0.9.20; extra == 'sample'
